redis_pal/RedisPal.py
redis_pal/__init__.py
redis_pal/exceptions.py
redis_pal-1.0.0.dist-info/LICENSE
redis_pal-1.0.0.dist-info/WHEEL
redis_pal-1.0.0.dist-info/METADATA
redis_pal-1.0.0.dist-info/RECORD
